sifflet_provider/__init__.py
sifflet_provider/get_provider_info.py
sifflet_provider/hooks/__init__.py
sifflet_provider/hooks/sifflet_hook.py
sifflet_provider/operators/__init__.py
sifflet_provider/operators/dbt.py
sifflet_provider/operators/rule.py
airflow_provider_sifflet-1.1.4.dist-info/METADATA
airflow_provider_sifflet-1.1.4.dist-info/WHEEL
airflow_provider_sifflet-1.1.4.dist-info/entry_points.txt
airflow_provider_sifflet-1.1.4.dist-info/top_level.txt
airflow_provider_sifflet-1.1.4.dist-info/RECORD
