Metadata-Version: 2.4
Name: airflow-provider-sifflet
Version: 1.1.4
Summary: Provider package airflow-provider-sifflet for Apache Airflow
Home-page: https://www.siffletdata.com/
Author: Sifflet
Author-email: support@siffletdata.com
License: Apache License 2.0
Classifier: Environment :: Console
Classifier: Intended Audience :: Developers
Classifier: Intended Audience :: System Administrators
Classifier: Framework :: Apache Airflow
Classifier: Framework :: Apache Airflow :: Provider
Requires-Python: ~=3.7
Requires-Dist: sifflet-sdk>=0.4.1
Provides-Extra: dev
Requires-Dist: apache-airflow; extra == "dev"
Dynamic: author
Dynamic: author-email
Dynamic: classifier
Dynamic: description
Dynamic: description-content-type
Dynamic: home-page
Dynamic: license
Dynamic: provides-extra
Dynamic: requires-dist
Dynamic: requires-python
Dynamic: summary
